Metadata-Version: 2.1
Name: aggr
Version: 0.1.2
Summary: Automate feature aggregation
Home-page: https://github.com/Daahorst/Aggregator
Author: François-Xavier Devailly, Xinyue Tan
Author-email: francois-xavier.devailly@hec.ca, xinyue.tan@hec.ca
License: MIT
Platform: UNKNOWN
